{
  "generatedAt": "2026-05-30T03:07:50+09:00",
  "weekly": {
    "commitCount": 12,
    "byDay": [
      {
        "date": "2026-05-24",
        "count": 2
      },
      {
        "date": "2026-05-25",
        "count": 2
      },
      {
        "date": "2026-05-26",
        "count": 2
      },
      {
        "date": "2026-05-27",
        "count": 2
      },
      {
        "date": "2026-05-28",
        "count": 2
      },
      {
        "date": "2026-05-29",
        "count": 2
      },
      {
        "date": "2026-05-30",
        "count": 0
      }
    ]
  },
  "byDirectory": {
    "scrap": 0,
    "ideas": 0,
    "health": 0,
    "books": 0,
    "portfolio": 0,
    "other": 18
  },
  "recentCommits": [
    {
      "date": "2026-05-29",
      "message": "news: 2026-05-29 記事まとめを自動生成"
    },
    {
      "date": "2026-05-29",
      "message": "朝刊: 2026-05-28 Morning Edition生成"
    },
    {
      "date": "2026-05-28",
      "message": "news: 2026-05-28 記事まとめを自動生成"
    },
    {
      "date": "2026-05-28",
      "message": "朝刊: 2026-05-27 Morning Edition生成"
    },
    {
      "date": "2026-05-27",
      "message": "news: 2026-05-27 記事まとめを自動生成"
    }
  ]
}