{
  "generatedAt": "2026-05-12T02:19:50+09:00",
  "weekly": {
    "commitCount": 12,
    "byDay": [
      {
        "date": "2026-05-06",
        "count": 2
      },
      {
        "date": "2026-05-07",
        "count": 2
      },
      {
        "date": "2026-05-08",
        "count": 2
      },
      {
        "date": "2026-05-09",
        "count": 2
      },
      {
        "date": "2026-05-10",
        "count": 2
      },
      {
        "date": "2026-05-11",
        "count": 2
      },
      {
        "date": "2026-05-12",
        "count": 0
      }
    ]
  },
  "byDirectory": {
    "scrap": 4,
    "ideas": 1,
    "health": 0,
    "books": 0,
    "portfolio": 0,
    "other": 56
  },
  "recentCommits": [
    {
      "date": "2026-05-11",
      "message": "news: 2026-05-11 記事まとめを自動生成"
    },
    {
      "date": "2026-05-11",
      "message": "朝刊: 2026-05-10 Morning Edition生成"
    },
    {
      "date": "2026-05-10",
      "message": "news: 2026-05-10 記事まとめを自動生成"
    },
    {
      "date": "2026-05-10",
      "message": "朝刊: 2026-05-09 Morning Edition生成"
    },
    {
      "date": "2026-05-09",
      "message": "news: 2026-05-09 記事まとめを自動生成"
    }
  ]
}